soulengine/__init__.py
soul_engine-0.1.0.dist-info/METADATA
soul_engine-0.1.0.dist-info/WHEEL
soul_engine-0.1.0.dist-info/licenses/LICENSE
soul_engine-0.1.0.dist-info/RECORD
